streamlit_paste_button/__init__.py
streamlit_paste_button/frontend/index.html
streamlit_paste_button/frontend/main.js
streamlit_paste_button/frontend/streamlit-component-lib.js
streamlit_paste_button/frontend/style.css
streamlit_paste_button-0.1.2.dist-info/LICENSE
streamlit_paste_button-0.1.2.dist-info/METADATA
streamlit_paste_button-0.1.2.dist-info/WHEEL
streamlit_paste_button-0.1.2.dist-info/top_level.txt
streamlit_paste_button-0.1.2.dist-info/RECORD
