Metadata-Version: 2.1
Name: streamlit-paste-button
Version: 0.1.2
Summary: Streamlit component that allows you to paste images from your clipboard into your app with a button click
Home-page: https://github.com/olucaslopes/streamlit-paste-button
Author: Lucas Lopes Amorim
Author-email: lucaslopesamorim@gmail.com
License: MIT
Project-URL: Documentation, https://github.com/olucaslopes/streamlit-paste-button/blob/main/README.md
Project-URL: Issue Tracker, https://github.com/olucaslopes/streamlit-paste-button/issues
Keywords: streamlit,component,paste,image,clipboard
Classifier: Development Status :: 5 - Production/Stable
Classifier: Environment :: Web Environment
Classifier: Intended Audience :: Developers
Classifier: License :: OSI Approved :: MIT License
Classifier: Programming Language :: Python :: 3
Classifier: Topic :: Desktop Environment
Classifier: Topic :: Multimedia :: Graphics
Classifier: Topic :: Software Development :: User Interfaces
Requires-Python: >=3.7
License-File: LICENSE
Requires-Dist: streamlit>=1.2
Requires-Dist: jinja2
Requires-Dist: pillow
